LICENSE
MANIFEST.in
README.md
setup.py
avcaesar_api/__init__.py
avcaesar_api/__main__.py
avcaesar_api.egg-info/PKG-INFO
avcaesar_api.egg-info/SOURCES.txt
avcaesar_api.egg-info/dependency_links.txt
avcaesar_api.egg-info/entry_points.txt
avcaesar_api.egg-info/requires.txt
avcaesar_api.egg-info/top_level.txt