Metadata-Version: 1.1
Name: avcaesar-api
Version: 1.0.3
Summary: library and tool for AVCaesar API
Home-page: https://github.com/MalwareLu/avcaesar-api-python-driver
Author: Stéphane Emma
Author-email: stephane@malware.lu
License: GPLv2
Keywords: avcaesar,api
Platform: UNKNOWN
Classifier: Environment :: Console
Classifier: License :: OSI Approved :: GNU General Public License v2 (GPLv2)
Classifier: Programming Language :: Python :: 3
